multiauthenticator.py
multiauthenticator-22.6.dist-info/LICENSE
multiauthenticator-22.6.dist-info/METADATA
multiauthenticator-22.6.dist-info/WHEEL
multiauthenticator-22.6.dist-info/top_level.txt
multiauthenticator-22.6.dist-info/RECORD
